mcp_server_stat/__init__.py
mcp_server_stat/__main__.py
mcp_server_stat/server.py
mcp_server_tb_project_stat-0.1.1.dist-info/METADATA
mcp_server_tb_project_stat-0.1.1.dist-info/WHEEL
mcp_server_tb_project_stat-0.1.1.dist-info/entry_points.txt
mcp_server_tb_project_stat-0.1.1.dist-info/top_level.txt
mcp_server_tb_project_stat-0.1.1.dist-info/RECORD
