Metadata-Version: 2.4
Name: mcp-server-tb-project-stat
Version: 0.1.1
Summary: tb-project-stat for mcp server, get project stat from tb
Requires-Python: >=3.10
Requires-Dist: fastmcp>=2.11.3
